{
  "song": "愛デンティティ",

  "memo": [
    "① 小嶋、上西、川上、山本望、安部",
    "芳賀塩月/泉、新澤/出口、瓶野坂田桜田、小嶋",
    "①サビ 新澤桜田、上西山本望、芳賀川上",
    "② 泉、塩月 (坂田)、上西小嶋新澤、山本望",
    "瓶野出口芳賀、桜田川上安部",
    "②サビ 小嶋出口、泉塩月、坂田瓶野",
    "ラストサビ 新澤/桜田、上西山本望、芳賀川上"
  ],

  "parts": [
    {
      "title": "イントロ",
      "lyrics": "",
      "members": [
        { "name": "kameno", "x": -6, "y": 1 },
        { "name": "haga", "x": -4, "y": 1 },
        { "name": "shiotsuki", "x": -2, "y": 1 },
        { "name": "shinzawa", "x": 0, "y": 1 },
        { "name": "sakata", "x": 2, "y": 1 },
        { "name": "deguchi", "x": 4, "y": 1 },
        { "name": "izumi", "x": 6, "y": 1 }
      ]
    },

    {
      "title": "1番Aメロ",
      "lyrics": "Shall we dance? チラリチラリズム〜",
      "members": [
        { "name": "kojima", "x": 0, "y": 3 },

        { "name": "kawakami", "x": 1.25, "y": 2 },
        { "name": "jonishi", "x": 1.25, "y": 2 },

        { "name": "abe", "x": 2.5, "y": 1 },
        { "name": "yamamoto", "x": 2.5, "y": 1 }
      ]
    },

    {
      "title": "1番サビ ①",
      "lyrics": "トップノートが愛デンティティ 私の絶対領域〜",
      "members": [
        { "name": "kameno", "x": -3.5, "y": 3 },
        { "name": "shinzawa", "x": -1, "y": 3 },
        { "name": "sakurada", "x": 1, "y": 3 },
        { "name": "deguchi", "x": 3.5, "y": 3 },

        { "name": "haga", "x": -5, "y": 2 },
        { "name": "izumi", "x": -2.5, "y": 2 },
        { "name": "kojima", "x": 0, "y": 2 },
        { "name": "sakata", "x": 2.5, "y": 2 },
        { "name": "yamamoto", "x": 5, "y": 2 },

        { "name": "kawakami", "x": -4, "y": 1 },
        { "name": "shiotsuki", "x": -1.5, "y": 1 },
        { "name": "abe", "x": 1.5, "y": 1 },
        { "name": "jonishi", "x": 4, "y": 1 }
      ]
    },

    {
      "title": "1番サビ ②",
      "lyrics": "本能で召し上がれ 焦っちゃだめよダーリン？〜",
      "members": [
        { "name": "haga", "x": -7.5, "y": 1 },
        { "name": "kawakami", "x": -6.25, "y": 1 },
        { "name": "kameno", "x": -5, "y": 1 },
        { "name": "izumi", "x": -3.75, "y": 1 },
        { "name": "shiotsuki", "x": -2.5, "y": 1 },
        { "name": "shinzawa", "x": -1.25, "y": 1 },
        { "name": "kojima", "x": 0, "y": 1 },
        { "name": "abe", "x": 1.25, "y": 1 },
        { "name": "sakurada", "x": 2.5, "y": 1 },
        { "name": "sakata", "x": 3.75, "y": 1 },
        { "name": "deguchi", "x": 5, "y": 1 },
        { "name": "jonishi", "x": 6.25, "y": 1 },
        { "name": "yamamoto", "x": 7.5, "y": 1 }
      ]
    },

    {
      "title": "2番Aメロ",
      "lyrics": "そのカラカラな喉に ツーーっと注がれるオアシス〜",
      "members": [
        { "name": "kojima", "x": -5, "y": 3 },
        { "name": "shinzawa", "x": -3, "y": 3 },
        { "name": "sakurada", "x": -1, "y": 3 },
        { "name": "kameno", "x": 1, "y": 3 },
        { "name": "abe", "x": 3, "y": 3 },
        { "name": "deguchi", "x": 5, "y": 3 },

        { "name": "jonishi", "x": -6, "y": 2 },
        { "name": "shiotsuki", "x": -2, "y": 2 },
        { "name": "izumi", "x": 2, "y": 2 },
        { "name": "kawakami", "x": 6, "y": 2 },

        { "name": "yamamoto", "x": -4, "y": 1 },
        { "name": "sakata", "x": 0, "y": 1 },
        { "name": "haga", "x": 4, "y": 1 }
      ]
    },

    {
      "title": "2番サビ ①",
      "lyrics": "トップノートが愛デンティティ 健全なアルゴリズム〜",
      "members": [
        { "name": "jonishi", "x": -3.5, "y": 3 },
        { "name": "kojima", "x": -1, "y": 3 },
        { "name": "deguchi", "x": 1, "y": 3 },
        { "name": "sakurada", "x": 3.5, "y": 3 },

        { "name": "sakata", "x": -5, "y": 2 },
        { "name": "shinzawa", "x": -2.5, "y": 2 },
        { "name": "kawakami", "x": 0, "y": 2 },
        { "name": "abe", "x": 2.5, "y": 2 },
        { "name": "shiotsuki", "x": 5, "y": 2 },

        { "name": "kameno", "x": -4, "y": 1 },
        { "name": "yamamoto", "x": -1.5, "y": 1 },
        { "name": "haga", "x": 1.5, "y": 1 },
        { "name": "izumi", "x": 4, "y": 1 }
      ]
    },

    {
      "title": "2番サビ ②",
      "lyrics": "気まぐれがいい感じ 焦っちゃだめよダーリン？〜",
      "members": [
        { "name": "sakata", "x": -7.5, "y": 1 },
        { "name": "kameno", "x": -6.25, "y": 1 },
        { "name": "jonishi", "x": -5, "y": 1 },
        { "name": "shinzawa", "x": -3.75, "y": 1 },
        { "name": "yamamoto", "x": -2.5, "y": 1 },
        { "name": "kojima", "x": -1.25, "y": 1 },
        { "name": "kawakami", "x": 0, "y": 1 },
        { "name": "deguchi", "x": 1.25, "y": 1 },
        { "name": "haga", "x": 2.5, "y": 1 },
        { "name": "abe", "x": 3.75, "y": 1 },
        { "name": "sakurada", "x": 5, "y": 1 },
        { "name": "izumi", "x": 6.25, "y": 1 },
        { "name": "shiotsuki", "x": 7.5, "y": 1 }
      ]
    },

    {
      "title": "ラストサビ ①",
      "lyrics": "トップノートが愛デンティティ 私の絶対領域〜",
      "members": [
        { "name": "kameno", "x": -3.5, "y": 3 },
        { "name": "shinzawa", "x": -1, "y": 3 },
        { "name": "sakurada", "x": 1, "y": 3 },
        { "name": "deguchi", "x": 3.5, "y": 3 },

        { "name": "haga", "x": -5, "y": 2 },
        { "name": "izumi", "x": -2.5, "y": 2 },
        { "name": "kojima", "x": 0, "y": 2 },
        { "name": "sakata", "x": 2.5, "y": 2 },
        { "name": "yamamoto", "x": 5, "y": 2 },

        { "name": "kawakami", "x": -4, "y": 1 },
        { "name": "shiotsuki", "x": -1.5, "y": 1 },
        { "name": "abe", "x": 1.5, "y": 1 },
        { "name": "jonishi", "x": 4, "y": 1 }
      ]
    },

    {
      "title": "ラストサビ ②",
      "lyrics": "本能で召し上がれ 焦っちゃだめよダーリン？〜",
      "members": [
        { "name": "haga", "x": -7.5, "y": 1 },
        { "name": "kawakami", "x": -6.25, "y": 1 },
        { "name": "kameno", "x": -5, "y": 1 },
        { "name": "izumi", "x": -3.75, "y": 1 },
        { "name": "shiotsuki", "x": -2.5, "y": 1 },
        { "name": "shinzawa", "x": -1.25, "y": 1 },
        { "name": "kojima", "x": 0, "y": 1 },
        { "name": "abe", "x": 1.25, "y": 1 },
        { "name": "sakurada", "x": 2.5, "y": 1 },
        { "name": "sakata", "x": 3.75, "y": 1 },
        { "name": "deguchi", "x": 5, "y": 1 },
        { "name": "jonishi", "x": 6.25, "y": 1 },
        { "name": "yamamoto", "x": 7.5, "y": 1 }
      ]
    }
  ]
}
